[{"name": "AreaBitFlags", "vals": [{"name": "Brinstar", "val": 1}, {"name": "Kraid", "val": 2}, {"name": "Norfair", "val": 4}, {"name": "Ridley", "val": 8}, {"name": "Tourian", "val": 16}, {"name": "Crateria", "val": 32}, {"name": "Chozodia", "val": 64}]}, {"name": "AreaId", "vals": [{"name": "Brinstar", "val": 0}, {"name": "Kraid", "val": 1}, {"name": "Norfair", "val": 2}, {"name": "Ridley", "val": 3}, {"name": "Tourian", "val": 4}, {"name": "Crateria", "val": 5}, {"name": "Chozodia", "val": 6}]}, {"name": "ArmCannonDirection", "vals": [{"name": "Forward", "val": 0}, {"name": "DiagonallyUp", "val": 1}, {"name": "DiagonallyDown", "val": 2}, {"name": "Up", "val": 3}, {"name": "Down", "val": 4}, {"name": "None", "val": 5}]}, {"name": "BackgroundFade", "vals": [{"name": "Nothing", "val": 0}, {"name": "FadeToBlack", "val": 1}, {"name": "FadeToWhite", "val": 2}]}, {"name": "BeamBombStatus", "vals": [{"name": "LongBeam", "val": 1}, {"name": "IceBeam", "val": 2}, {"name": "WaveBeam", "val": 4}, {"name": "PlasmaBeam", "val": 8}, {"name": "ChargeBeam", "val": 16}, {"name": "Bombs", "val": 128}]}, {"name": "BeforeAfterEventFlag", "vals": [{"name": "After", "val": 0}, {"name": "Before", "val": 1}]}, {"name": "BgProperty", "vals": [{"name": "None", "val": 0}, {"name": "RleCompressed", "val": 16}, {"name": "MovingBg2", "val": 49}, {"name": "Lz77Compressed", "val": 64}, {"name": "DarkRoom", "val": 69}, {"name": "Bg3StartsFromBottom", "val": 70}]}, {"name": "BlockReformType", "vals": [{"name": "None", "val": 0}, {"name": "NoOrNeverReform", "val": 1}, {"name": "Reform", "val": 2}, {"name": "BombChain", "val": 3}, {"name": "Tank", "val": 4}]}, {"name": "BlockWeaknessFlags", "vals": [{"name": "None", "val": 0}, {"name": "Beam", "val": 1}, {"name": "BombOrPistol", "val": 2}, {"name": "Missile", "val": 4}, {"name": "SuperMissile", "val": 8}, {"name": "PowerBomb", "val": 16}, {"name": "SpeedBoost", "val": 32}, {"name": "SpeedBoost_Ground", "val": 64}, {"name": "ScrewAttack", "val": 128}, {"name": "BombChain", "val": 4096}]}, {"name": "BombChainType", "vals": [{"name": "Vertical1", "val": 0}, {"name": "Vertical2", "val": 1}, {"name": "Vertical3", "val": 2}, {"name": "Vertical4", "val": 3}, {"name": "Horizontal1", "val": 4}, {"name": "Horizontal2", "val": 5}, {"name": "Horizontal3", "val": 6}, {"name": "Horizontal4", "val": 7}]}, {"name": "BombVisibility", "vals": [{"name": "None", "val": 0}, {"name": "unk_01", "val": 1}, {"name": "BombsActivated", "val": 2}, {"name": "HasPowerBombs", "val": 4}, {"name": "MorphBallActivated", "val": 8}]}, {"name": "BreakableBlockType", "vals": [{"name": "None", "val": 0}, {"name": "ShotBlock_Reform", "val": 1}, {"name": "BombBlock_Reform", "val": 2}, {"name": "SpeedBooster_Reform", "val": 3}, {"name": "Crumble", "val": 4}, {"name": "SlowCrumble", "val": 5}, {"name": "Missile_NeverReform", "val": 6}, {"name": "Missile_NoReform", "val": 7}, {"name": "SuperMissile_NeverReform", "val": 8}, {"name": "SuperMissile_NoReform", "val": 9}, {"name": "PowerBomb_NeverReform", "val": 10}, {"name": "ScrewAttack_NoReform", "val": 11}, {"name": "SpeedBooster_NoReform", "val": 12}, {"name": "Bomb_NeverReform", "val": 13}, {"name": "VerticalBombChain1", "val": 14}, {"name": "VerticalBombChain2", "val": 15}, {"name": "VerticalBombChain3", "val": 16}, {"name": "VerticalBombChain4", "val": 17}, {"name": "HorizontalBombChain1", "val": 18}, {"name": "HorizontalBombChain2", "val": 19}, {"name": "HorizontalBombChain3", "val": 20}, {"name": "HorizontalBombChain4", "val": 21}]}, {"name": "ButtonInput", "vals": [{"name": "A", "val": 1}, {"name": "B", "val": 2}, {"name": "Select", "val": 4}, {"name": "Start", "val": 8}, {"name": "Right", "val": 16}, {"name": "Left", "val": 32}, {"name": "Up", "val": 64}, {"name": "Down", "val": 128}, {"name": "R", "val": 256}, {"name": "L", "val": 512}]}, {"name": "ChozoHintCheckType", "vals": [{"name": "BeamBombs", "val": 0}, {"name": "SuitMisc", "val": 1}, {"name": "Event", "val": 2}]}, {"name": "ChozoHintIcon", "vals": [{"name": "Target", "val": 1}, {"name": "UpElevator", "val": 2}, {"name": "DownElevator", "val": 3}, {"name": "GreenFlame", "val": 8}, {"name": "GreenFlame_MovesUpDown", "val": 10}, {"name": "PinkFlame", "val": 12}, {"name": "PinkFlame_MovesUpDown", "val": 14}]}, {"name": "ChozoHintLocation", "vals": [{"name": "LongBeam", "val": 1}, {"name": "Bombs", "val": 2}, {"name": "IceBeam", "val": 4}, {"name": "SpeedBooster", "val": 8}, {"name": "HiJump", "val": 16}, {"name": "VariaSuit", "val": 32}, {"name": "WaveBeam", "val": 64}, {"name": "ScrewAttack", "val": 128}, {"name": "KraidFlame", "val": 256}, {"name": "RidleyFlame", "val": 512}]}, {"name": "ClipdataAffectingAction", "vals": [{"name": "RemoveSolid", "val": 1}, {"name": "MakeSolid", "desc": "Sets clip to 0x43E", "val": 2}, {"name": "MakeStopEnemy", "desc": "Sets clip to 0x43D", "val": 3}, {"name": "MakeNonPowerGrip", "desc": "Sets clip to 0x43F", "val": 4}, {"name": "BombChain_Unused", "val": 5}, {"name": "Unused", "val": 6}, {"name": "Beam", "val": 7}, {"name": "BombPistol", "val": 8}, {"name": "Missile", "val": 9}, {"name": "SuperMissile", "val": 10}, {"name": "PowerBomb", "val": 11}, {"name": "SpeedBoost", "val": 12}, {"name": "SpeedBoost_Ground", "val": 13}, {"name": "ScrewAttack", "val": 14}, {"name": "BombChain", "val": 15}]}, {"name": "ClipdataBehaviorType", "vals": [{"name": "AirOrSolid", "val": 0}, {"name": "ElevatorDownBlock", "val": 1}, {"name": "ElevatorUpBlock", "val": 2}, {"name": "DoorTransitionBlock", "val": 3}, {"name": "VerticalUpTransitionBlock", "val": 4}, {"name": "VerticalDownTransitionBlock", "val": 5}, {"name": "NonPowerGrip", "val": 6}, {"name": "StopEnemyBlock_Solid", "val": 7}, {"name": "SpacePirateZoneline", "val": 8}, {"name": "SpacePirateWallJumpPoint", "val": 9}, {"name": "ShotBlock_NeverReform", "val": 16}, {"name": "TopLeftShotBlock_NeverReform", "val": 17}, {"name": "TopRightShotBlock_NeverReform", "val": 18}, {"name": "BottomLeftShotBlock_NeverReform", "val": 19}, {"name": "BottomRightShotBlock_NeverReform", "val": 20}, {"name": "ShotBlock_NoReform", "val": 21}, {"name": "TopLeftShotBlock_NoReform", "val": 22}, {"name": "TopRightShotBlock_NoReform", "val": 23}, {"name": "BottomLeftShotBlock_NoReform", "val": 24}, {"name": "BottomRightShotBlock_NoReform", "val": 25}, {"name": "ShotBlock_Reform", "val": 26}, {"name": "BombBlock_NeverReform", "val": 27}, {"name": "BombBlock_Reform", "val": 28}, {"name": "MissileBlock_NeverReform", "val": 29}, {"name": "MissileBlock_NoReform", "val": 30}, {"name": "SuperMissileBlock_NeverReform", "val": 31}, {"name": "SuperMissileBlock_NoReform", "val": 32}, {"name": "SpeedBoostBlock_NoReform", "val": 33}, {"name": "SpeedBoostBlock_Reform", "val": 34}, {"name": "CrumbleBlock", "val": 35}, {"name": "PowerBombBlock_NeverReform", "val": 36}, {"name": "ScrewAttackBlock_NoReform", "val": 37}, {"name": "VerticalBombChain1", "val": 38}, {"name": "VerticalBombChain2", "val": 39}, {"name": "VerticalBombChain3", "val": 40}, {"name": "VerticalBombChain4", "val": 41}, {"name": "HorizontalBombChain1", "val": 42}, {"name": "HorizontalBombChain2", "val": 43}, {"name": "HorizontalBombChain3", "val": 44}, {"name": "HorizontalBombChain4", "val": 45}, {"name": "SlowCrumbleBlock", "val": 46}, {"name": "HiddenEnergyTank", "val": 52}, {"name": "HiddenMissleTank", "val": 53}, {"name": "HiddenSuperMissleTank", "val": 54}, {"name": "HiddenPowerBombTank", "val": 55}, {"name": "EnergyTank", "val": 56}, {"name": "MissleTank", "val": 57}, {"name": "SuperMissleTank", "val": 58}, {"name": "PowerBombTank", "val": 59}, {"name": "UnderwaterEnergyTank", "val": 60}, {"name": "UnderwaterMissileTank", "val": 61}, {"name": "UnderwaterSuperMissileTank", "val": 62}, {"name": "UnderwaterPowerBombTank", "val": 63}, {"name": "Water", "val": 64}, {"name": "StrongLava", "val": 65}, {"name": "WeakLava", "val": 66}, {"name": "Acid", "val": 67}, {"name": "Bg0TriggerOpaque", "val": 68}, {"name": "Bg0TriggerTransparentLevel1", "val": 69}, {"name": "Bg0TriggerTransparentLevel2", "val": 70}, {"name": "Bg0TriggerTransparentLevel3", "val": 71}, {"name": "Bg0TriggerTransparentLevel4", "val": 72}, {"name": "Bg0TriggerTransparentLevel5", "val": 73}, {"name": "Bg0Trigger100Transparent", "val": 74}, {"name": "Bg0TriggerBrighter1", "val": 75}, {"name": "Bg0TriggerBrighter2", "val": 76}, {"name": "Bg0TriggerBrighter3", "val": 77}, {"name": "Bg0TriggerBrighter4", "val": 78}, {"name": "Bg0TriggerDefaultTransparency", "val": 79}, {"name": "WetGround", "val": 80}, {"name": "DustyGround", "val": 81}, {"name": "UnusedSolid_1E", "val": 82}, {"name": "BubblyGround", "val": 83}, {"name": "VeryDustyGround", "val": 84}, {"name": "GrayDoor", "val": 128}, {"name": "RegularDoor", "val": 129}, {"name": "MissileDoor", "val": 130}, {"name": "SuperMissileDoor", "val": 131}, {"name": "PowerBombDoor", "val": 132}]}, {"name": "ClipdataCollisionType", "vals": [{"name": "Air", "val": 0}, {"name": "Solid", "val": 1}, {"name": "LeftSteepFloorSlope", "val": 2}, {"name": "RightSteepFloorSlope", "val": 3}, {"name": "LeftUpperSlightFloorSlope", "val": 4}, {"name": "LeftLowerSlightFloorSlope", "val": 5}, {"name": "RightLowerSlightFloorSlope", "val": 6}, {"name": "RightUpperSlightFloorSlope", "val": 7}, {"name": "EnemyOnly", "val": 8}, {"name": "StopEnemyBlock", "val": 9}, {"name": "Tank", "val": 10}, {"name": "Hatch", "val": 11}, {"name": "PassThroughBottom", "val": 12}]}, {"name": "CollisionCheck", "vals": [{"name": "AirOrNoCollision", "val": 0}, {"name": "LeftSlightFloorSlope", "val": 2}, {"name": "RightSlightFloorSlope", "val": 3}, {"name": "LeftSteepFloorSlope", "val": 4}, {"name": "RightSteepFloorSlope", "val": 5}, {"name": "PassThroughBottom", "val": 16}, {"name": "SolidOrCollision", "val": 17}]}, {"name": "Cutscene", "vals": [{"name": "None", "val": 0}, {"name": "SamusIntroText", "val": 1}, {"name": "SamusZebesEscapeText", "val": 2}, {"name": "SamusZebesEscapeFinalText", "val": 3}, {"name": "MotherBrainCloseUp", "desc": "Triggered when entering Norfair", "val": 4}, {"name": "KraidFightStart", "val": 5}, {"name": "TourianElevatorStatueActivating", "val": 6}, {"name": "RidleyInSpace", "desc": "Triggered when leaving Kraid", "val": 7}, {"name": "RidleyLanding", "desc": "Triggered when entering Ridley", "val": 8}, {"name": "RidleyFightStart", "val": 9}, {"name": "TourianMetroids", "desc": "Triggered when entering Tourian", "val": 10}, {"name": "BeforeRuinsTestFight", "desc": "Triggered when entering Ruins Test room", "val": 11}, {"name": "ObtainingFullyPoweredSuit", "val": 12}, {"name": "MechaRidleySeesSamus", "desc": "Triggered when entering mother ship", "val": 13}, {"name": "ActivatingEscapeShip", "val": 14}]}, {"name": "CutsceneRequest", "vals": [{"name": "None", "val": 0}, {"name": "EscapingChozodia", "val": 1}, {"name": "EscapedFailed", "val": 2}, {"name": "EscapingZebes", "val": 3}, {"name": "ObtainingFullyPoweredSuit", "val": 4}, {"name": "RidleyFightStart", "val": 5}, {"name": "TourianElevatorStatueActivating", "val": 6}, {"name": "SamusIntroText", "val": 7}, {"name": "ActivatingEscapeShip", "val": 8}]}, {"name": "CutsceneSpecialEffectStatus", "vals": [{"name": "None", "val": 0}, {"name": "OnObj", "val": 1}, {"name": "ObjEffectEnded", "val": 2}, {"name": "OnBg", "val": 4}, {"name": "BgEffectEnded", "val": 8}]}, {"name": "DebrisCloudType", "vals": [{"name": "TODO", "val": 0}]}, {"name": "DemoState", "vals": [{"name": "None", "val": 0}, {"name": "Recording", "val": 1}, {"name": "Playing", "val": 2}, {"name": "Loading", "val": 3}]}, {"name": "DemoStatus", "vals": [{"name": "None", "val": 0}, {"name": "Playing", "val": 1}, {"name": "Loading", "val": 16}]}, {"name": "DiagonalAim", "vals": [{"name": "None", "val": 0}, {"name": "DiagonallyUp", "val": 1}, {"name": "DiagonallyDown", "val": 2}]}, {"name": "Difficulty", "vals": [{"name": "Easy", "val": 0}, {"name": "Normal", "val": 1}, {"name": "Hard", "val": 2}]}, {"name": "Direction", "vals": [{"name": "Right", "val": 16}, {"name": "Left", "val": 32}, {"name": "Up", "val": 64}, {"name": "Down", "val": 128}]}, {"name": "DoorType", "vals": [{"name": "AreaConnection", "val": 1}, {"name": "NoHatch", "val": 2}, {"name": "OpenHatch", "val": 3}, {"name": "ClosedHatch", "val": 4}, {"name": "RemoveMotherShip", "val": 5}, {"name": "SetMotherShip", "val": 6}, {"name": "LoadsEventBasedRoom", "val": 32}, {"name": "DisplaysLocationName", "val": 64}]}, {"name": "Elevator", "vals": [{"name": "None", "val": 0}, {"name": "CrateriaToBrinstar_Unused", "val": 1}, {"name": "BrinstarToNorfair", "val": 2}, {"name": "BrinstarToKraid", "val": 3}, {"name": "NorfairToRidley", "val": 4}, {"name": "BrinstarToTourian", "val": 5}, {"name": "CrateriaToTourian", "val": 6}, {"name": "CrateriaToNorfair", "val": 7}]}, {"name": "EndingFlags", "vals": [{"name": "None", "val": 0}, {"name": "NewTimeAttackRecord", "val": 1}, {"name": "Unused", "val": 16}, {"name": "FirstTimeAttackClear", "val": 32}, {"name": "FirstHardModeClear", "val": 64}, {"name": "FirstClear", "val": 128}]}, {"name": "ErrorFlags", "vals": [{"name": "None", "val": 0}, {"name": "unk_03", "val": 3}, {"name": "unk_1C", "val": 28}, {"name": "unk_20", "val": 32}, {"name": "unk_40", "val": 64}, {"name": "unk_E00", "val": 3584}, {"name": "HardwareError", "val": 65536}, {"name": "ChecksumError", "val": 131072}, {"name": "SendOverflow", "val": 262144}, {"name": "ReceiveOverflow", "val": 524288}, {"name": "SioInternalError", "val": 1048576}, {"name": "SioStopError", "val": 2097152}, {"name": "IdOverError", "val": 4194304}]}, {"name": "EscapeTimerStatus", "vals": [{"name": "None", "val": 0}, {"name": "EscapeHappening", "val": 1}, {"name": "EscapeFailed", "val": 2}]}, {"name": "Event", "vals": [{"name": "None", "val": 0}, {"name": "EasyMode", "val": 1}, {"name": "HardMode", "val": 2}, {"name": "EnterNorfairDemoPlayed", "val": 3}, {"name": "ExitKraidDemoPlayed", "val": 4}, {"name": "EnterRidleyDemoPlayed", "val": 5}, {"name": "EnterMotherShipDemoPlayed", "val": 6}, {"name": "EnterTourianDemoPlayed", "val": 7}, {"name": "GrabbedByChozoInBrinstar_ShowsLongBeam", "val": 8}, {"name": "GrabbedByChozoInBrinstar_ShowsBombs", "val": 9}, {"name": "GrabbedByChozoInBrinstar_ShowsIceBeam", "val": 10}, {"name": "GrabbedByChozoInNorfair_ShowsSpeedBooster", "val": 11}, {"name": "GrabbedByChozoInBrinstar_ShowsHiJump", "val": 12}, {"name": "GrabbedByChozoInNorfair_ShowsVariaSuit", "val": 13}, {"name": "GrabbedByChozoInBrinstar_ShowsWave", "val": 14}, {"name": "GrabbedByChozo_ShowsScrewAttack_Unused", "val": 15}, {"name": "PowerGripObtained", "val": 16}, {"name": "ChozoPillarFullyExtended", "val": 17}, {"name": "HiJumpObtained", "val": 18}, {"name": "VariaSuitObtained", "val": 19}, {"name": "ChargeBeamObtained", "val": 20}, {"name": "ScrewAttackObtained", "val": 21}, {"name": "SpaceJumpObtained", "val": 22}, {"name": "GravitySuitObtained", "val": 23}, {"name": "PlasmaBeamObtained", "val": 24}, {"name": "ChargeBeamBossEncounteredAtFirstLocationOrKilled", "val": 25}, {"name": "ChargeBeamBossEncounteredAtSecondLocationOrKilled", "val": 26}, {"name": "ChargeBeamBossKilledAtSecondLocation", "val": 27}, {"name": "AcidWormKilled", "val": 28}, {"name": "KraidEyedoorKilled", "val": 29}, {"name": "KraidKilled", "val": 30}, {"name": "KraidElevatorStatueDestroyed", "val": 31}, {"name": "CaterpillarKilled", "val": 32}, {"name": "ImagoTunnelDiscovered", "val": 33}, {"name": "CocoonKilled", "val": 34}, {"name": "ImagoKilled", "val": 35}, {"name": "RidleyEyedoorKilled", "val": 36}, {"name": "RidleyKilled", "val": 37}, {"name": "RidleyElevatorStatueDestroyed", "val": 38}, {"name": "MotherBrainKilled", "val": 39}, {"name": "CrocomireKilled_Unused", "val": 40}, {"name": "RepelMachineKilled_Unused", "val": 41}, {"name": "ViewedStatueRoomAfterLongBeam", "val": 42}, {"name": "DessgeegaKilledAfterStatueRoom", "val": 43}, {"name": "AllThreeHivesDestroyed", "val": 44}, {"name": "BugsKilledAfterBombs", "val": 45}, {"name": "ZiplinesActivated", "val": 46}, {"name": "PlantDestroyed_InLava", "val": 47}, {"name": "PlantDestroyed_PostVaria", "val": 48}, {"name": "PlantDestroyed_Varia2", "val": 49}, {"name": "PlantDestroyed_Varia3", "val": 50}, {"name": "PlantDestroyed_Varia1", "val": 51}, {"name": "KraidBaristutesDead", "val": 52}, {"name": "KraidStatueOpened", "val": 53}, {"name": "RidleyStatueOpened", "val": 54}, {"name": "MetroidRoom1Cleared", "val": 55}, {"name": "MetroidRoom3Cleared", "val": 56}, {"name": "MetroidRoom5Cleared", "val": 57}, {"name": "MetroidRoom2Cleared", "val": 58}, {"name": "MetroidRoom6Cleared", "val": 59}, {"name": "MetroidRoom4Cleared", "val": 60}, {"name": "Zebetite1Destroyed", "val": 61}, {"name": "Zebetite2Destroyed", "val": 62}, {"name": "Zebetite3Destroyed", "val": 63}, {"name": "Zebetite4Destroyed", "val": 64}, {"name": "EscapedZebes", "val": 65}, {"name": "MarkerBetweenZebesAndMotherShipEvents", "val": 66}, {"name": "FullyPoweredSuitObtained", "val": 67}, {"name": "SkippedVariaSuit", "val": 68}, {"name": "Unknown_ChozoBlock", "desc": "Debug text says \"CHOZOBLOCK\"", "val": 69}, {"name": "PowerBombStolen", "val": 70}, {"name": "SpacePirateWithPowerBomb1", "val": 71}, {"name": "SpacePirateWithPowerBomb2", "val": 72}, {"name": "GlassTubeBroken", "val": 73}, {"name": "MechaRidleyKilled", "val": 74}, {"name": "EscapedChozodia", "val": 75}, {"name": "Unknown_Aki", "desc": "Debug text says \"AKI\" (\"open\")", "val": 76}, {"name": "Unknown_BombGate", "desc": "Debug text says \"BOMBGATE\"", "val": 77}, {"name": "End_Unused", "val": 78}]}, {"name": "FileSelectCursorState", "vals": [{"name": "Default", "val": 0}, {"name": "Moving", "val": 1}, {"name": "OpeningOptions", "val": 2}, {"name": "SelectingFile", "val": 5}, {"name": "DeselectingFile", "val": 6}, {"name": "StartingGame", "val": 7}, {"name": "unk_08", "val": 8}]}, {"name": "FloatingPointClass", "vals": [{"name": "SignalingNan", "val": 0}, {"name": "QuietNan", "val": 1}, {"name": "Zero", "val": 2}, {"name": "Num", "val": 3}, {"name": "Infinity", "val": 4}]}, {"name": "ForcedMovement", "vals": [{"name": "NoneSparkingUpwards", "val": 0}, {"name": "BouncingWallJumpingSparkingSidewards", "val": 1}, {"name": "SparkingDiagonally", "val": 2}, {"name": "HoldingJumpWhenBouncing_Frame1", "val": 32}, {"name": "HoldingJumpWhenBouncing_Frame2", "val": 33}, {"name": "HoldingJumpWhenBouncing_Frame3", "val": 34}]}, {"name": "GameMode", "vals": [{"name": "SoftReset", "val": 0}, {"name": "Intro", "val": 1}, {"name": "Title", "val": 2}, {"name": "FileSelect", "val": 3}, {"name": "InGame", "val": 4}, {"name": "MapItemScreen", "val": 5}, {"name": "GameOver", "val": 6}, {"name": "ChozodiaEscape", "val": 7}, {"name": "Credits", "val": 8}, {"name": "TourianEscape", "val": 9}, {"name": "Cutscenes", "val": 10}, {"name": "Demo", "val": 11}, {"name": "Gallery", "val": 12}, {"name": "MetroidFusionGallery", "val": 13}, {"name": "SoftResetWithInput", "val": 14}, {"name": "EraseSramMenu", "val": 15}, {"name": "DebugMenu_BetaOnly", "val": 16}]}, {"name": "GraphicsAnimType", "vals": [{"name": "NotAnimated", "val": 0}, {"name": "Normal", "val": 1}, {"name": "Alt", "val": 4}]}, {"name": "GroundTypeUnderSamus", "vals": [{"name": "Normal", "val": 0}, {"name": "WetGround", "val": 1}, {"name": "DustyGround", "val": 2}, {"name": "VeryDustyGround", "val": 3}, {"name": "Behavior52_Unused", "val": 4}, {"name": "BubblyGround", "val": 5}]}, {"name": "HatchStatus", "vals": [{"name": "Opening", "val": 1}, {"name": "Opened", "val": 2}, {"name": "Locked", "val": 4}, {"name": "unk_08", "val": 8}, {"name": "Flashing1", "val": 16}, {"name": "Flashing2", "val": 32}, {"name": "Flashing3", "val": 64}]}, {"name": "HatchType", "vals": [{"name": "None", "val": 0}, {"name": "Unused", "val": 1}, {"name": "Normal", "val": 2}, {"name": "Missile", "val": 3}, {"name": "SuperMissile", "val": 4}, {"name": "PowerBomb", "val": 5}, {"name": "Locked", "val": 6}, {"name": "Locked_NotGray", "val": 7}]}, {"name": "HazardType", "vals": [{"name": "None", "val": 0}, {"name": "Water", "val": 1}, {"name": "StrongLava", "val": 2}, {"name": "WeakLava", "val": 3}, {"name": "Acid", "val": 4}, {"name": "Heat", "val": 5}, {"name": "Cold_Knockback", "val": 6}, {"name": "Cold", "val": 7}]}, {"name": "HazeType", "vals": [{"name": "None", "val": 0}, {"name": "GradientRelated", "val": 1}, {"name": "Bg3", "val": 2}, {"name": "Bg3_StrongInEffect_WeakOutside", "val": 3}, {"name": "Bg3_NoneInEffect_WeakOutside", "val": 4}, {"name": "Bg3_Bg2_StrongInEffectWeakOutsideForBg3", "val": 5}, {"name": "Bg1_Bg2_Bg3", "desc": "Used by room effect 0xC", "val": 6}, {"name": "PowerBombExpanding", "val": 7}, {"name": "PowerBombRetracting", "val": 8}, {"name": "AfterPowerBomb", "val": 9}, {"name": "ColdSnowflakes_NoEffect", "val": 10}]}, {"name": "InGameCutscene", "vals": [{"name": "CloseUp", "val": 4}, {"name": "GettingVaria", "val": 9}, {"name": "GettingFullyPowered", "val": 10}]}, {"name": "ItemType", "vals": [{"name": "MissileTank", "val": 1}, {"name": "EnergyTank", "val": 2}, {"name": "SuperMissileTank", "val": 3}, {"name": "PowerBombTank", "val": 4}, {"name": "Ability", "val": 128}]}, {"name": "Language", "vals": [{"name": "Japanese_Kanji", "val": 0}, {"name": "Japanese_Hiragana", "val": 1}, {"name": "English", "val": 2}]}, {"name": "LiquidType", "vals": [{"name": "None", "val": 0}, {"name": "Water", "val": 1}, {"name": "StrongLava", "val": 2}, {"name": "WeakLava", "val": 3}, {"name": "Acid", "val": 4}]}, {"name": "Lz77BackgroundSize", "vals": [{"name": "Size_256_256", "val": 0}, {"name": "Size_512_256", "val": 1}, {"name": "Size_256_512", "val": 2}]}, {"name": "MapScreenFadingStage", "vals": [{"name": "None", "val": 0}, {"name": "FadingInInit", "val": 2}, {"name": "FadingIn", "val": 3}, {"name": "FadingOutInit", "val": 4}, {"name": "FadingOut", "val": 5}]}, {"name": "MapScreenSubroutineType", "vals": [{"name": "MapScreen", "val": 0}, {"name": "StatusOrDebugScreen", "val": 1}, {"name": "SuitlessItems", "val": 4}, {"name": "FullyPoweredItems", "val": 6}, {"name": "ChozoStatueHint", "val": 8}, {"name": "MapDownload", "val": 9}, {"name": "EasySleepScreen", "val": 10}, {"name": "StatusScreenInit", "val": 11}, {"name": "LeavingStatusScreen", "val": 12}, {"name": "EasySleepInit", "val": 16}, {"name": "LeavingEasySleep", "val": 17}, {"name": "SuitlessItemsInit", "val": 19}, {"name": "FullyPoweredItemsInit", "val": 20}]}, {"name": "MapScreenType", "vals": [{"name": "None", "val": 0}, {"name": "Debug", "val": 1}, {"name": "OnMapScreen", "val": 2}, {"name": "unk_08", "val": 8}, {"name": "ChozoStatueHint", "val": 16}, {"name": "DownloadingMap", "val": 32}, {"name": "OnStatusScreen", "val": 128}, {"name": "GettingNewItem", "val": 256}, {"name": "GettingSuitless", "val": 512}, {"name": "GettingFullyPowered", "val": 1024}]}, {"name": "MapTankStatus", "vals": [{"name": "None", "val": 0}, {"name": "MaxEnergyTanks", "val": 1}, {"name": "MaxMissileTanks", "val": 2}, {"name": "MaxSuperMissileTanks", "val": 4}, {"name": "MaxPowerBombTanks", "val": 8}]}, {"name": "MenuSoundId", "vals": [{"name": "SubMenuCursor", "val": 0}, {"name": "AcceptConfirmMenu", "val": 1}, {"name": "MenuCurosr", "val": 2}, {"name": "FileSelect", "val": 3}, {"name": "StartGame", "val": 4}, {"name": "OpenSubMenu", "val": 5}, {"name": "CloseSubMenu", "val": 6}, {"name": "CloseSubMenu", "val": 7}, {"name": "FileSelectCopyDelete", "val": 8}, {"name": "FileSelectCopyDeleteMoving", "val": 9}, {"name": "FileCopyConfirm", "val": 10}, {"name": "MenuCursor", "val": 11}, {"name": "StartGame", "val": 12}]}, {"name": "MovementPreventingClipdata", "vals": [{"name": "None", "val": 0}, {"name": "ElevatorDownBlock", "val": 1}, {"name": "ElevatorUpBlock", "val": 2}, {"name": "PreventPowerGrip", "val": 6}, {"name": "SolidStopEnemyBlock", "val": 7}, {"name": "SpacePirateZoneline", "val": 8}, {"name": "SpacePirateWallJumpPoint", "val": 9}]}, {"name": "NewProjectileType", "vals": [{"name": "None", "val": 0}, {"name": "Beam", "val": 1}, {"name": "Missile", "val": 2}, {"name": "SuperMissile", "val": 3}, {"name": "Bomb", "val": 4}, {"name": "PowerBomb", "val": 5}, {"name": "ChargedBeam", "val": 6}]}, {"name": "OamPreAction", "vals": [{"name": "None", "val": 0}, {"name": "ChangeFrame", "val": 1}, {"name": "ResetFrame", "val": 2}, {"name": "LoopOnLastFrame", "val": 3}, {"name": "DeleteAfterEnd", "val": 4}, {"name": "IncrementIdAfterEnd", "val": 5}, {"name": "unk_06", "val": 6}, {"name": "unk_07", "val": 7}, {"name": "SwitchToPrevFrame", "val": 8}, {"name": "DecrementIdAtBeginning", "val": 9}]}, {"name": "OamStatus", "vals": [{"name": "None", "val": 0}, {"name": "unk_02", "val": 2}, {"name": "LoopingOnLastFrame", "val": 16}, {"name": "NotDrawn", "val": 32}, {"name": "Exists", "val": 64}, {"name": "OamIdChanged", "val": 128}]}, {"name": "PaletteAnimType", "vals": [{"name": "NotAnimated", "val": 0}, {"name": "Normal", "val": 1}, {"name": "Alternate", "val": 2}]}, {"name": "ParticleEffect", "vals": [{"name": "SpriteSplashWaterSmall", "val": 0}, {"name": "SpriteSplashWaterBig", "val": 1}, {"name": "SpriteSplashWaterHuge", "val": 2}, {"name": "SpriteSplashLavaSmall", "val": 3}, {"name": "SpriteSplashLavaBig", "val": 4}, {"name": "SpriteSplashLavaHuge", "val": 5}, {"name": "SpriteSplashAcidSmall", "val": 6}, {"name": "SpriteSplashAcidBig", "val": 7}, {"name": "SpriteSplashAcidHuge", "val": 8}, {"name": "ShootingBeamLeft", "val": 9}, {"name": "ShootingBeamDiagonallyUpLeft", "val": 10}, {"name": "ShootingBeamDiagonallyDownLeft", "val": 11}, {"name": "ShootingBeamUpLeft", "val": 12}, {"name": "ShootingBeamDownLeft", "val": 13}, {"name": "ShootingBeamRight", "val": 14}, {"name": "ShootingBeamDiagonallyUpRight", "val": 15}, {"name": "ShootingBeamDiagonallyDownRight", "val": 16}, {"name": "ShootingBeamUpRight", "val": 17}, {"name": "ShootingBeamDownRight", "val": 18}, {"name": "Bomb", "val": 19}, {"name": "MissileTrail", "val": 20}, {"name": "SuperMissileTrail", "val": 21}, {"name": "BeamTrailingRight", "val": 22}, {"name": "BeamTrailingLeft", "val": 23}, {"name": "ChargedLongBeamTrail", "val": 24}, {"name": "ChargedIceBeamTrail", "val": 25}, {"name": "ChargedWaveBeamTrail", "val": 26}, {"name": "ChargedPlasmaBeam", "val": 27}, {"name": "ChargedFullBeamTrail", "val": 28}, {"name": "ChargedPistolTrail", "val": 29}, {"name": "SpriteExplosionHuge", "val": 30}, {"name": "SpriteExplosionSmall", "val": 31}, {"name": "SpriteExplosionMedium", "val": 32}, {"name": "SpriteExplosionBig", "val": 33}, {"name": "SpriteExplosionSingleThenBig", "val": 34}, {"name": "ScrewAttackDestroyed", "val": 35}, {"name": "ShinesparkDestroyed", "val": 36}, {"name": "SudoScrewAttackDestroyed", "val": 37}, {"name": "SpeedboosterDestroyed", "val": 38}, {"name": "MainBossDeath", "val": 39}, {"name": "FreezingSpriteWithIce", "val": 40}, {"name": "FreezingSpriteWithChargedIce", "val": 41}, {"name": "HittingSomethingWithBaseBeamOrChargedBase", "val": 42}, {"name": "HittingSomethingWithLongBeamOrChargedLong", "val": 43}, {"name": "HittingSomethingWithIceBeam", "val": 44}, {"name": "HittingSomethingWithWaveBeam", "val": 45}, {"name": "HittingSomethingWithPlasmaBeam", "val": 46}, {"name": "HittingSomethingInvincible", "val": 47}, {"name": "HittingSomethingWithMissile", "val": 48}, {"name": "HittingSomethingWithSuperMissile", "val": 49}, {"name": "HittingSomethingWithFullBeamNoPlasma", "val": 50}, {"name": "HittingSomethingWithFullBeam", "val": 51}, {"name": "SmallDust1", "val": 52}, {"name": "MediumDust1", "val": 53}, {"name": "TwoMediumDust1", "val": 54}, {"name": "SmallDust2", "val": 55}, {"name": "MediumDust2", "val": 56}, {"name": "TwoMediumDust2", "val": 57}, {"name": "SamusReflection", "val": 58}, {"name": "ChargingBeam", "val": 59}, {"name": "Escape", "val": 60}]}, {"name": "ParticleEffectStatus", "vals": [{"name": "Exists", "val": 1}, {"name": "OnScreen", "val": 2}, {"name": "IsExplosion", "val": 4}, {"name": "NotDrawn", "val": 8}, {"name": "LiveOffScreen", "val": 16}, {"name": "LowBgPriority", "val": 32}, {"name": "AbsolutePosition", "val": 64}, {"name": "XFlip", "val": 128}]}, {"name": "PauseScreenFlag", "vals": [{"name": "unk_01", "val": 1}, {"name": "PauseScreenCutscenes", "val": 2}, {"name": "unk_03", "val": 3}, {"name": "ChozoStatueHint", "val": 4}, {"name": "MapDownload", "val": 5}, {"name": "ItemAcquisition", "val": 6}, {"name": "SuitlessItems", "val": 7}, {"name": "FullyPoweredSuitItems", "val": 8}]}, {"name": "PrimarySpriteId", "vals": [{"name": "Unused_00", "val": 0}, {"name": "Unused_01", "val": 1}, {"name": "Unused_02", "val": 2}, {"name": "Unused_03", "val": 3}, {"name": "Unused_04", "val": 4}, {"name": "Unused_05", "val": 5}, {"name": "Unused_06", "val": 6}, {"name": "Unused_07", "val": 7}, {"name": "Unused_08", "val": 8}, {"name": "Unused_09", "val": 9}, {"name": "Unused_0A", "val": 10}, {"name": "Unused_0B", "val": 11}, {"name": "Unused_0C", "val": 12}, {"name": "Unused_0D", "val": 13}, {"name": "Unused_0E", "val": 14}, {"name": "Unused_0F", "val": 15}, {"name": "Unused_10", "val": 16}, {"name": "ItemBanner", "val": 17}, {"name": "Zoomer_Yellow", "val": 18}, {"name": "Zoomer_Red", "val": 19}, {"name": "Zeela", "val": 20}, {"name": "Zeela_Red", "val": 21}, {"name": "Ripper_Brown", "val": 22}, {"name": "Ripper_Purple", "val": 23}, {"name": "Zeb", "val": 24}, {"name": "Zeb_Blue", "val": 25}, {"name": "LargeEnergy", "val": 26}, {"name": "SmallEnergy", "val": 27}, {"name": "MissileDrop", "val": 28}, {"name": "SuperMissileDrop", "val": 29}, {"name": "PowerBombDrop", "val": 30}, {"name": "Skree_Green", "val": 31}, {"name": "Skree_Blue", "val": 32}, {"name": "MorphBall", "val": 33}, {"name": "ChozoStatue_LongBeamHint", "val": 34}, {"name": "LongBeamChozoStatue", "val": 35}, {"name": "ChozoStatue_IceBeamHint", "val": 36}, {"name": "IceBeamChozoStatue", "val": 37}, {"name": "ChozoStatue_WaveBeamHint", "val": 38}, {"name": "WaveBeamChozoStatue", "val": 39}, {"name": "ChozoStatue_BombHint", "val": 40}, {"name": "BombChozoStatue", "val": 41}, {"name": "ChozoStatue_SpeedBoosterHint", "val": 42}, {"name": "SpeedBoosterChozoStatue", "val": 43}, {"name": "ChozoStatue_HiJumpHint", "val": 44}, {"name": "HiJumpChozoStatue", "val": 45}, {"name": "ChozoStatue_ScrewAttackHint", "val": 46}, {"name": "ScrewAttackChozoStatue", "val": 47}, {"name": "ChozoStatue_VariaSuitHint", "val": 48}, {"name": "VariaSuitChozoStatue", "val": 49}, {"name": "Sova_Purple", "val": 50}, {"name": "Sova_Orange", "val": 51}, {"name": "Multiviola", "val": 52}, {"name": "MultipleLargeEnergy", "val": 53}, {"name": "Geruta_Red", "val": 54}, {"name": "Geruta_Green", "val": 55}, {"name": "Squeept", "val": 56}, {"name": "Squeept_Unused", "val": 57}, {"name": "MapStation", "val": 58}, {"name": "Dragon", "val": 59}, {"name": "Dragon_Unused", "val": 60}, {"name": "Zipline", "val": 61}, {"name": "ZiplineButton", "val": 62}, {"name": "Reo_GreenWings", "val": 63}, {"name": "Reo_PurpleWings", "val": 64}, {"name": "Gunship", "val": 65}, {"name": "Deorem", "val": 66}, {"name": "Deorem_SecondLocation", "val": 67}, {"name": "ChargeBeam", "val": 68}, {"name": "Skultera", "val": 69}, {"name": "Dessgeega", "val": 70}, {"name": "Dessgeega_AfterLongBeam", "val": 71}, {"name": "Waver", "val": 72}, {"name": "Waver_Unused", "val": 73}, {"name": "Mellow", "val": 74}, {"name": "Hive", "val": 75}, {"name": "PowerGrip", "val": 76}, {"name": "ImagoLarva_Right", "val": 77}, {"name": "MorphBallLauncher", "val": 78}, {"name": "ImagoCocoon", "val": 79}, {"name": "ElevatorPad", "val": 80}, {"name": "SpacePirate", "val": 81}, {"name": "SpacePirate_Waiting", "val": 82}, {"name": "SpacePirate_Waiting", "val": 83}, {"name": "SpacePirate_Waiting", "val": 84}, {"name": "SpacePirate", "val": 85}, {"name": "Gamet_Blue_Single", "val": 86}, {"name": "Gamet_Red_Single", "val": 87}, {"name": "GravitySuitChozoStatue", "val": 88}, {"name": "SpaceJumpChozoStatue", "val": 89}, {"name": "SecurityGate_DefaultOpen", "val": 90}, {"name": "Zebbo_Green", "val": 91}, {"name": "Zebbo_Yellow", "val": 92}, {"name": "WorkerRobot", "val": 93}, {"name": "Parasite_Multiple", "val": 94}, {"name": "Parasite", "val": 95}, {"name": "Piston", "val": 96}, {"name": "Ridley", "val": 97}, {"name": "SecurityGate_DefaultClosed", "val": 98}, {"name": "ZiplineGenerator", "val": 99}, {"name": "Metroid", "val": 100}, {"name": "FrozenMetroid", "val": 101}, {"name": "Rinka_Orange", "val": 102}, {"name": "Polyp", "val": 103}, {"name": "Viola_Blue", "val": 104}, {"name": "Viola_Orange", "val": 105}, {"name": "Geron_Norfair", "val": 106}, {"name": "Holtz", "val": 107}, {"name": "GekitaiMachine", "val": 108}, {"name": "RuinsTest", "val": 109}, {"name": "SavePlatform", "val": 110}, {"name": "Kraid", "val": 111}, {"name": "ImagoCocoon_AfterFight", "val": 112}, {"name": "Ripper2", "val": 113}, {"name": "Mella", "val": 114}, {"name": "Atomic", "val": 115}, {"name": "AreaBanner", "val": 116}, {"name": "MotherBrain", "val": 117}, {"name": "FakePowerBombEventTrigger", "val": 118}, {"name": "AcidWorm", "val": 119}, {"name": "EscapeShip", "val": 120}, {"name": "Sidehopper", "val": 121}, {"name": "Geega", "val": 122}, {"name": "Geega_White", "val": 123}, {"name": "Rinka_MotherBrain", "val": 124}, {"name": "Zebetite1And3", "val": 125}, {"name": "Cannon", "val": 126}, {"name": "ImagoLarva_RightSide", "val": 127}, {"name": "TangleVine_Tall", "val": 128}, {"name": "TangleVine_Medium", "val": 129}, {"name": "TangleVine_Curved", "val": 130}, {"name": "TangleVine_Short", "val": 131}, {"name": "Mellow_Swarm", "val": 132}, {"name": "Mellow_Swarm_HealthBased", "val": 133}, {"name": "Imago", "val": 134}, {"name": "Zebetite2And4", "val": 135}, {"name": "Cannon", "val": 136}, {"name": "Cannon", "val": 137}, {"name": "Crocomire", "val": 138}, {"name": "ImagoLarva_Left", "val": 139}, {"name": "Geron_Brinstar15", "val": 140}, {"name": "Geron_Brinstar1C", "val": 141}, {"name": "Geron_Varia1", "val": 142}, {"name": "Geron_Varia2", "val": 143}, {"name": "Geron_Varia3", "val": 144}, {"name": "GlassTube", "val": 145}, {"name": "SavePlatform_Chozodia", "val": 146}, {"name": "Baristute", "val": 147}, {"name": "PlasmaBeamChozoStatue", "val": 148}, {"name": "KraidElevatorStatue", "val": 149}, {"name": "RidleyElevatorStatue", "val": 150}, {"name": "RisingChozoPillar", "val": 151}, {"name": "SecurityLaser_Vertical", "val": 152}, {"name": "SecurityLaser_Horizontal", "val": 153}, {"name": "SecurityLaser_Vertical", "val": 154}, {"name": "SecurityLaser_Horizontal", "val": 155}, {"name": "LockUnlockMetroidDoors_Unused", "val": 156}, {"name": "Gamet_Blue_Leader", "val": 157}, {"name": "Gamet_Blue_Follower", "val": 158}, {"name": "Geega_Leader", "val": 159}, {"name": "Geega_Follower", "val": 160}, {"name": "Zebbo_Green_Leader", "val": 161}, {"name": "Zebbo_Green_Follower", "val": 162}, {"name": "KraidStatue", "val": 163}, {"name": "RidleyStatue", "val": 164}, {"name": "Rinka_Green", "val": 165}, {"name": "SearchlightEye", "val": 166}, {"name": "SearchlightEye", "val": 167}, {"name": "Steam_Large", "val": 168}, {"name": "Steam_Small", "val": 169}, {"name": "PlasmaBeamBlock", "val": 170}, {"name": "GravitySuitBlock", "val": 171}, {"name": "SpaceJumpBlock", "val": 172}, {"name": "Gadora_Kraid", "val": 173}, {"name": "Gadora_Ridley", "val": 174}, {"name": "Searchlight", "val": 175}, {"name": "Searchlight", "val": 176}, {"name": "Searchlight", "val": 177}, {"name": "Searchlight", "val": 178}, {"name": "SearchlightTrigger", "val": 179}, {"name": "EventTrigger_DiscoveredImagoPassage", "val": 180}, {"name": "FakePowerBomb", "val": 181}, {"name": "SpacePirateCarryingPowerBomb", "val": 182}, {"name": "TangleVine_Red_Geruta", "val": 183}, {"name": "TangleVine_Geruta", "val": 184}, {"name": "TangleVine_Larva_Right", "val": 185}, {"name": "TangleVine_Larva_Left", "val": 186}, {"name": "WaterDrop", "val": 187}, {"name": "FallingChozoPillar", "val": 188}, {"name": "MechaRidley", "val": 189}, {"name": "Explosions_ZebesEscape", "val": 190}, {"name": "Steam_Large_DiagonalUp", "val": 191}, {"name": "Steam_Small_DiagonalUp", "val": 192}, {"name": "Steam_Large_DiagonalDown", "val": 193}, {"name": "Steam_Small_DiagonalDown", "val": 194}, {"name": "Baristute_Kraid_Upper", "val": 195}, {"name": "EscapeGate1", "val": 196}, {"name": "EscapeGate2", "val": 197}, {"name": "BlackSpacePirate", "val": 198}, {"name": "EscapeShipSpacePirate", "val": 199}, {"name": "Baristute_Kraid_Lower", "val": 200}, {"name": "Rinka_MotherBrain", "val": 201}, {"name": "Rinka_MotherBrain", "val": 202}, {"name": "Rinka_MotherBrain", "val": 203}, {"name": "Rinka_MotherBrain", "val": 204}, {"name": "Rinka_MotherBrain", "val": 205}]}, {"name": "ProjectileStatus", "vals": [{"name": "Exists", "val": 1}, {"name": "OnScreen", "val": 2}, {"name": "NotDrawn", "val": 4}, {"name": "IgnoreCollision", "val": 8}, {"name": "CanAffectEnvironment", "val": 16}, {"name": "YFlip", "val": 32}, {"name": "XFlip", "val": 64}, {"name": "DrawUnderSpites", "val": 128}]}, {"name": "ProjectileType", "vals": [{"name": "Beam", "val": 0}, {"name": "LongBeam", "val": 1}, {"name": "IceBeam", "val": 2}, {"name": "WaveBeam", "val": 3}, {"name": "PlasmaBeam", "val": 4}, {"name": "Pistol", "val": 5}, {"name": "ChargeBeam", "val": 6}, {"name": "ChargedLongBeam", "val": 7}, {"name": "ChargedIceBeam", "val": 8}, {"name": "ChargedWaveBeam", "val": 9}, {"name": "ChargedPlasmaBeam", "val": 10}, {"name": "ChargedPistol", "val": 11}, {"name": "Missile", "val": 12}, {"name": "SuperMissile", "val": 13}, {"name": "Bomb", "val": 14}, {"name": "PowerBomb", "val": 15}]}, {"name": "RoomEffect", "vals": [{"name": "None", "val": 0}, {"name": "Water", "val": 1}, {"name": "StrongLava", "val": 2}, {"name": "WeakLava", "val": 3}, {"name": "StrongLava_HeatDamage_Bg3Haze", "val": 4}, {"name": "Acid", "val": 5}, {"name": "Snowflakes_ColdDamage_Knockback", "val": 6}, {"name": "Snowflakes_ColdDamage", "val": 7}, {"name": "HeatHazeBg3", "val": 8}, {"name": "HeatHaze_Bg2_Bg3", "val": 9}, {"name": "Gradient_Bg3", "val": 10}, {"name": "Gradient_Bg2", "val": 11}, {"name": "HeatHaze_Bg1_Bg2_Bg3", "val": 12}]}, {"name": "SamusEnvironmentEffect", "vals": [{"name": "None", "val": 0}, {"name": "RunningOnWetGround", "val": 1}, {"name": "RunningOnDustyGround", "val": 2}, {"name": "RunningOnVeryDustyGround", "val": 3}, {"name": "ExitingWater", "val": 4}, {"name": "RunningIntoWater", "val": 5}, {"name": "ExitingLava", "val": 6}, {"name": "RunningIntoLava", "val": 7}, {"name": "ExitingAcid", "val": 8}, {"name": "RunningIntoAcid", "val": 9}, {"name": "TakingDamageInLava", "val": 10}, {"name": "TakingDamageInAcid", "val": 11}, {"name": "LandingOnWetGround", "val": 12}, {"name": "LandingOnBubblyGround", "val": 13}, {"name": "LandingOnDustyGround", "val": 14}, {"name": "LandingOnVeryDustyGround", "val": 15}, {"name": "SkiddingOnWetGround", "val": 16}, {"name": "SkiddingOnDustyGround", "val": 17}, {"name": "BreathingBubbles", "val": 18}]}, {"name": "SamusPose", "vals": [{"name": "Running", "val": 0}, {"name": "Standing", "val": 1}, {"name": "TurningAround", "val": 2}, {"name": "Shooting", "val": 3}, {"name": "Crouching", "val": 4}, {"name": "TurningAroundAndCrouching", "val": 5}, {"name": "ShootingAndCrouching", "val": 6}, {"name": "Skidding", "val": 7}, {"name": "JumpingFalling", "val": 8}, {"name": "TurningAroundAndJumpingFalling", "val": 9}, {"name": "Landing", "val": 10}, {"name": "StartingSpinJump", "val": 11}, {"name": "Spinning", "val": 12}, {"name": "StartingWallJump", "val": 13}, {"name": "SpaceJumping", "val": 14}, {"name": "ScrewAttacking", "val": 15}, {"name": "Morphing", "val": 16}, {"name": "Morphball", "val": 17}, {"name": "Rolling", "val": 18}, {"name": "Unmorphing", "val": 19}, {"name": "JumpingFallingInMorphball", "val": 20}, {"name": "HangingOnLedge", "val": 21}, {"name": "TurningToAimWhileHanging", "val": 22}, {"name": "HidingArmCanonWhileHanging", "val": 23}, {"name": "AimingWhileHanging", "val": 24}, {"name": "ShootingWhileHanging", "val": 25}, {"name": "PullingSelfUpFromHanging", "val": 26}, {"name": "PullingSelfForwardFromHanging", "val": 27}, {"name": "PullingSelfIntoMorphballTunnel", "val": 28}, {"name": "UsingElevator", "val": 29}, {"name": "FacingTheForeground", "val": 30}, {"name": "TurningFromFacingForeground", "val": 31}, {"name": "GrabbedByChozoStatue", "val": 32}, {"name": "DelayBeforeShinesparking", "val": 33}, {"name": "Shinesparking", "val": 34}, {"name": "ShinesparkCollision", "val": 35}, {"name": "DelayAfterShinesparking", "val": 36}, {"name": "DelayBeforeBallsparking", "val": 37}, {"name": "Ballsparking", "val": 38}, {"name": "BallsparkCollision", "val": 39}, {"name": "OnZipline", "val": 40}, {"name": "ShootingOnZipline", "val": 41}, {"name": "TurningOnZipline", "val": 42}, {"name": "MorphballOnZipline", "val": 43}, {"name": "SavingLoadingGame", "val": 44}, {"name": "DownloadingMapData", "val": 45}, {"name": "TurningAroundToDownloadMapData", "val": 46}, {"name": "GettingHurt", "val": 47}, {"name": "GettingKnockedBack", "val": 48}, {"name": "GettingHurtInMorphball", "val": 49}, {"name": "GettingKnockedBackInMorphball", "val": 50}, {"name": "Dying", "val": 51}, {"name": "CrouchingToCrawlSuitless", "val": 52}, {"name": "CrawlingStopped", "val": 53}, {"name": "StartingToCrawl", "val": 54}, {"name": "Crawling", "val": 55}, {"name": "UncrouchingFromCrawling", "val": 56}, {"name": "TurningAroundWhileCrawling", "val": 57}, {"name": "ShootingWhileCrawling", "val": 58}, {"name": "Uncrouching_Suitless", "val": 59}, {"name": "Crouching_Suitless", "val": 60}, {"name": "GrabbingLedge_Suitless", "val": 61}, {"name": "FacingTheBg_Suitless", "val": 62}, {"name": "TuringFromFacingTheBg_Suitless", "val": 63}, {"name": "ActivatingZiplines", "val": 64}, {"name": "InEscapeShip", "val": 65}, {"name": "TurningToEnterEscapeShip", "val": 66}, {"name": "KnockbackPoseRequest", "val": 249}, {"name": "HurtPoseRequest", "val": 250}, {"name": "LandingPoseRequest", "val": 253}, {"name": "UpdateJumpVelocityRequest", "val": 254}, {"name": "None", "val": 255}]}, {"name": "SamusSlopeType", "vals": [{"name": "Steep", "desc": "45 degree angle", "val": 1}, {"name": "Slight", "desc": "26.5 degree angle", "val": 2}, {"name": "Right", "desc": "Fills the bottom right of a block", "val": 16}, {"name": "Left", "desc": "Fills the bottom left of a block", "val": 32}]}, {"name": "SamusStandingStatus", "vals": [{"name": "StandingOnGround", "val": 0}, {"name": "StandingOnEnemy", "val": 1}, {"name": "Midair", "val": 2}, {"name": "NotInControlOfSamus", "val": 3}, {"name": "ForcedPose", "val": 4}, {"name": "Hanging", "val": 5}]}, {"name": "ScrollsFlag", "vals": [{"name": "NoScrolls", "val": 2}, {"name": "RoomHasScrolls", "val": 3}]}, {"name": "SecondarySpriteId", "vals": [{"name": "ChozoBall", "val": 0}, {"name": "ChozoStatueBody", "val": 1}, {"name": "ChozoStatueRefill", "val": 2}, {"name": "KraidMouth", "val": 3}, {"name": "ChozoStatueMovement", "val": 4}, {"name": "ChargeBeamGlow", "val": 5}, {"name": "WingedRipper", "val": 6}, {"name": "UnusedMultiviolaSprite", "val": 7}, {"name": "DragonFireball", "val": 8}, {"name": "DeoremSegment", "val": 9}, {"name": "DeoremEye", "val": 10}, {"name": "DeoremThorn", "val": 11}, {"name": "Skree_Green_Explosion", "val": 12}, {"name": "SavePlatformTop", "val": 13}, {"name": "SaveYesNoCursor", "val": 14}, {"name": "Skree_Blue_Explosion", "val": 15}, {"name": "ZeelaEyes", "val": 16}, {"name": "HiveRoots", "val": 17}, {"name": "ImagoLarva_Outside", "val": 18}, {"name": "MorphBall_Outside", "val": 19}, {"name": "ImagoCocoonVine", "val": 20}, {"name": "ImagoCocoonSpore", "val": 21}, {"name": "SpacePirateLaser", "val": 22}, {"name": "RidleyBody", "val": 23}, {"name": "RidleyTail", "val": 24}, {"name": "SearchlightEyeBeam", "val": 25}, {"name": "MetroidShell", "val": 26}, {"name": "PolypProjectile", "val": 27}, {"name": "KraidSpikes", "val": 28}, {"name": "KraidNails", "val": 29}, {"name": "ZiplineGeneratorPart", "val": 30}, {"name": "AtomicElectricity", "val": 31}, {"name": "MotherBrainEye", "val": 32}, {"name": "RidleyFireballSmall", "val": 33}, {"name": "UnknownItemChozoStatueBody", "val": 34}, {"name": "UnknownItemChozoStatueRefillRelated", "val": 35}, {"name": "MorphBallLauncher_Back", "val": 36}, {"name": "AcidWormBody", "val": 37}, {"name": "AcidWormSpit", "val": 38}, {"name": "CannonBullet", "val": 39}, {"name": "CrocomireBody", "val": 40}, {"name": "ImagoBody", "val": 41}, {"name": "DefeatedImagoCocoon_Unused", "val": 42}, {"name": "ImagoCocoonRoot", "val": 43}, {"name": "SearchlightEyeBeam", "val": 44}, {"name": "Geruta_TangleVine", "val": 45}, {"name": "SavePlatformTop_Chozodia", "val": 46}, {"name": "ImagoNeedle", "val": 47}, {"name": "ElevatorStatueDebris", "val": 48}, {"name": "ImagoDamagedStinger", "val": 49}, {"name": "GunshipPart", "val": 50}, {"name": "ImagoEgg", "val": 51}, {"name": "MapStationScreen", "val": 52}, {"name": "ChozoPillarPlatform", "val": 53}, {"name": "GadoraEye", "val": 54}, {"name": "GadoraBeam", "val": 55}, {"name": "UnknownItemBlockLight", "val": 56}, {"name": "SearchlightEyeProjectile", "val": 57}, {"name": "ChozoPillarPlatformShadow", "val": 58}, {"name": "RuinsTestSymbol", "val": 59}, {"name": "RuinsTestSamusReflection_Start", "val": 60}, {"name": "RuinsTestReflectionCover", "val": 61}, {"name": "RuinsTestGhostOutline", "val": 62}, {"name": "RuinsTestGhost", "val": 63}, {"name": "RuinsTestShootableSymbol", "val": 64}, {"name": "RuinsTestSamusReflection_End", "val": 65}, {"name": "RuinsTestLightning", "val": 66}, {"name": "RidleyFireballLarge", "val": 67}, {"name": "MechaRidleyPart", "val": 68}, {"name": "EscapeShipPart", "val": 69}, {"name": "PowerGripGlow", "val": 70}, {"name": "MechaRidleyLaser", "val": 71}, {"name": "MechaRidleyMissile", "val": 72}, {"name": "MechaRidleyFireball", "val": 73}, {"name": "MotherBrainBeam", "val": 74}, {"name": "MotherBrainBlock", "val": 75}, {"name": "MotherBrainGlassBreaking", "val": 76}]}, {"name": "SpecialBgEffect", "vals": [{"name": "None", "val": 0}, {"name": "Lightning", "val": 1}, {"name": "SlightYellow", "val": 2}, {"name": "HeavyYellow", "val": 3}, {"name": "TourianFade", "val": 4}, {"name": "IntroTextFade", "val": 5}, {"name": "QuickFlash", "val": 6}, {"name": "AllBlack", "val": 7}, {"name": "AllWhite", "val": 8}]}, {"name": "SpecialBgEffectBehavior", "vals": [{"name": "WaitForTimer_Unused", "val": 0}, {"name": "WaitForTimer_RNG", "val": 1}, {"name": "WaitForTimer", "val": 2}, {"name": "CheckApplyFirstColor", "val": 3}, {"name": "CheckApplySecondColor", "val": 4}, {"name": "PlaySound", "val": 5}, {"name": "EndAndClear", "desc": "Sets type to 0", "val": 6}, {"name": "End", "val": 7}, {"name": "EndExitZebesEffect", "val": 8}, {"name": "EndBeforeIntroTextEffect", "val": 9}]}, {"name": "SpecialBgFadeType", "vals": [{"name": "None", "val": 0}, {"name": "Flash", "val": 1}, {"name": "unk_02", "val": 2}, {"name": "White", "val": 3}, {"name": "DoorTransition", "val": 4}, {"name": "Flash2", "val": 5}, {"name": "NoTransition", "val": 6}, {"name": "FlashNoTransition", "val": 7}, {"name": "NoTransitionHudHide", "val": 8}, {"name": "SlowWhiteFade", "val": 9}, {"name": "SlowBlackFade", "val": 10}, {"name": "AfterEnterMotherShipCutscene", "val": 11}, {"name": "EscapeFailedFade", "val": 12}, {"name": "DemoEndingAutomaticallyFade", "val": 13}, {"name": "DemoEndingFromInputFade", "val": 14}, {"name": "ChozodiaEscapeFade", "val": 15}, {"name": "TourianEscapeFade", "val": 16}, {"name": "GettingFullyPoweredFade", "val": 17}, {"name": "BeforeRidleyFightFade", "val": 18}, {"name": "StatueCutsceneFade", "val": 19}, {"name": "IntroTextFade", "val": 20}, {"name": "LandingShipCutsceneFade", "val": 21}, {"name": "BlueShipFade", "val": 22}, {"name": "ToWhite", "val": 23}, {"name": "ToBlack", "val": 24}]}, {"name": "SpriteDebrisType", "vals": [{"name": "TODO", "val": 0}]}, {"name": "SpriteProperties", "vals": [{"name": "AlwaysActive_IgnorePreventMovementTimer", "val": 1}, {"name": "unk_02", "val": 2}, {"name": "KillOffScreen", "desc": "Delete sprite if it moves off screen", "val": 4}, {"name": "SolidForProjectiles", "val": 8}, {"name": "Destroyed", "val": 16}, {"name": "AbsolutePosition", "val": 32}, {"name": "ImmuneToProjectiles", "val": 64}, {"name": "SecondarySprite", "val": 128}]}, {"name": "SpriteSamusCollision", "vals": [{"name": "Solid", "val": 1}, {"name": "EscapeShip", "val": 2}, {"name": "HurtsSamus_CanStandOn", "val": 3}, {"name": "HurtsSamus", "val": 4}, {"name": "AtomicDischarge", "val": 5}, {"name": "HurtsSamus_StopsWhenHit", "val": 6}, {"name": "KnocksBackSamus", "val": 7}, {"name": "HurtsSamus_NoKnockback", "val": 9}, {"name": "Kraid", "val": 10}, {"name": "HurtsSamus_CannotPassThrough", "val": 11}, {"name": "Zebetite", "val": 12}, {"name": "ImagoStinger", "val": 13}, {"name": "HurtsSamus_BigKnockback_StopsWhenHit", "val": 14}, {"name": "HurtsSamus_NoKnockback_StopsWhenHit", "val": 16}, {"name": "HurtsSamus_NoKnockback_IgnoreContactDamage", "val": 17}, {"name": "Mellow", "val": 18}, {"name": "SpacePirateLaser", "val": 19}, {"name": "SpacePirate", "val": 20}, {"name": "AcidWorm", "val": 21}, {"name": "AcidWormMouth", "val": 22}, {"name": "Bug", "val": 23}, {"name": "Metroid", "val": 24}, {"name": "KraidSpike", "val": 25}, {"name": "Zipline", "val": 26}, {"name": "ImagoEgg", "val": 27}, {"name": "RidleyClaw_CanBeGrabbed", "val": 28}, {"name": "MechaRidley", "val": 29}, {"name": "Ability_SecurityLaser_Searchlight", "val": 30}, {"name": "SmallEnergyDrop", "val": 31}, {"name": "LargeEnergyDrop", "val": 32}, {"name": "MissileDrop", "val": 33}, {"name": "SuperMissileDrop", "val": 34}, {"name": "PowerBombDrop", "val": 35}, {"name": "MultipleLargeEnergyDrop", "val": 36}]}, {"name": "SpriteStatus", "vals": [{"name": "Exists", "val": 1}, {"name": "OnScreen", "val": 2}, {"name": "NotDrawn", "val": 4}, {"name": "RotationScalingFlag", "val": 8}, {"name": "unk_10", "val": 16}, {"name": "MosaicFlag", "val": 32}, {"name": "XFlip", "val": 64}, {"name": "unk_80", "val": 128}, {"name": "YFlip", "val": 256}, {"name": "FacingRight", "val": 512}, {"name": "unk_400", "val": 1024}, {"name": "SamusColliding", "val": 2048}, {"name": "SamusOnTop", "val": 4096}, {"name": "AlphaBlending", "val": 8192}, {"name": "DoubleSize", "val": 16384}, {"name": "IgnoreProjectiles", "val": 32768}]}, {"name": "SpriteWeakness", "vals": [{"name": "ChargeBeamPistol_NoNormalBeam", "val": 1}, {"name": "BeamAndBombs", "val": 2}, {"name": "SuperMissiles_NoNormalMissiles", "val": 4}, {"name": "Missiles", "val": 8}, {"name": "PowerBombs", "val": 16}, {"name": "SpeedBoosterScrewAttack", "val": 32}, {"name": "CanBeFrozen", "val": 64}]}, {"name": "SuitMiscStatus", "vals": [{"name": "HiJump", "val": 1}, {"name": "SpeedBooster", "val": 2}, {"name": "SpaceJump", "val": 4}, {"name": "ScrewAttack", "val": 8}, {"name": "VariaSuit", "val": 16}, {"name": "GravitySuit", "val": 32}, {"name": "MorphBall", "val": 64}, {"name": "PowerGrip", "val": 128}]}, {"name": "SuitType", "vals": [{"name": "Normal", "val": 0}, {"name": "FullyPowered", "val": 1}, {"name": "Suitless", "val": 2}]}, {"name": "UpdateMinimapFlag", "vals": [{"name": "None", "val": 0}, {"name": "UpdateTopLine", "val": 1}, {"name": "UpdateMiddleLine", "val": 2}, {"name": "UpdateBottomLine", "val": 3}]}]