[{"name": "BackgroundEffectBehaviorEntry_T", "type": "const u16 [0x3]", "loc": "include/structs/animated_graphics.h:65"}, {"name": "BlockFunc_T", "type": "u32 (*)(struct ClipdataBlockData *)", "loc": "include/structs/block.h:65"}, {"name": "ChozodiaEscapeFunc_T", "type": "u8 (*)(void)", "loc": "include/data/internal_chozodia_escape_data.h:6"}, {"name": "ClipFunc_T", "type": "u32 (*)(struct CollisionData *)", "loc": "include/structs/clipdata.h:41"}, {"name": "ColorFadingFunc_T", "type": "u8 (*)(u8, u8)", "loc": "include/structs/color_effects.h:8"}, {"name": "ColorFadingUnkFunc_T", "type": "u8 (*)(void)", "loc": "include/structs/color_effects.h:9"}, {"name": "CreditsFunc_T", "type": "u8 (*)(void)", "loc": "include/data/internal_ending_and_gallery_data.h:6"}, {"name": "CutsceneFunc_T", "type": "u8 (*)(void)", "loc": "include/structs/cutscene.h:37"}, {"name": "Func_T", "type": "void (*)(void)", "loc": "include/types.h:98"}, {"name": "HazeFunc_T", "type": "u32 (*)(void)", "loc": "include/structs/haze.h:6"}, {"name": "InGameCutsceneFunc_T", "type": "u32 (*)(u8, u8)", "loc": "include/structs/in_game_cutscene.h:6"}, {"name": "IntroFunc_T", "type": "u8 (*)(void)", "loc": "include/structs/intro.h:40"}, {"name": "MinimapFunc_T", "type": "void (*)(u32 *, u16 *, u8)", "loc": "include/structs/minimap.h:10"}, {"name": "MultiSpriteDataInfo_T", "type": "const s16 (*)[0x3]", "loc": "include/structs/sprite.h:19"}, {"name": "MusicFunc_T", "type": "void (*)(struct TrackVariables *)", "loc": "include/structs/audio.h:264"}, {"name": "NesEmuFunc_T", "type": "void (*)(void *)", "loc": "include/data/nes_metroid.h:6"}, {"name": "OptionsFunc_T", "type": "u8 (*)(void)", "loc": "include/structs/menus/file_select.h:14"}, {"name": "ParticleFunc_T", "type": "void (*)(struct ParticleEffect *)", "loc": "include/structs/particle.h:22"}, {"name": "ProjFunc_T", "type": "void (*)(struct ProjectileData *)", "loc": "include/structs/projectile.h:37"}, {"name": "SamusFunc_T", "type": "u8 (*)(struct SamusData *)", "loc": "include/structs/samus.h:178"}, {"name": "SoundCodeAFunc_T", "type": "void (*)(struct SoundChannel *, u32 *, u8)", "loc": "include/structs/audio.h:301"}, {"name": "SoundCodeBFunc_T", "type": "u8 * (*)(u32 *, u32 *, u32 *, u8)", "loc": "include/structs/audio.h:302"}, {"name": "SoundCodeCFunc_T", "type": "u8 * (*)(u32 *, u32 *, u8)", "loc": "include/structs/audio.h:303"}, {"name": "SramStructSize", "type": "char [0x1]", "loc": "include/structs/save_file.h:238"}, {"name": "TimeAttackFunc_T", "type": "void (*)(u8 *, s32)", "loc": "include/structs/time_attack.h:7"}, {"name": "TourianEscapeFunc_T", "type": "u8 (*)(void)", "loc": "include/data/internal_tourian_escape_data.h:7"}, {"name": "s16", "type": "signed short", "loc": "include/types.h:11"}, {"name": "s32", "type": "signed int", "loc": "include/types.h:13"}, {"name": "s64", "type": "signed long long", "loc": "include/types.h:15"}, {"name": "s8", "type": "signed char", "loc": "include/types.h:9"}, {"name": "u16", "type": "unsigned short", "loc": "include/types.h:10"}, {"name": "u32", "type": "unsigned int", "loc": "include/types.h:12"}, {"name": "u64", "type": "unsigned long long", "loc": "include/types.h:14"}, {"name": "u8", "type": "unsigned char", "loc": "include/types.h:8"}, {"name": "vs16", "type": "volatile signed short", "loc": "include/types.h:19"}, {"name": "vs32", "type": "volatile signed int", "loc": "include/types.h:21"}, {"name": "vs64", "type": "volatile signed long long", "loc": "include/types.h:23"}, {"name": "vs8", "type": "volatile signed char", "loc": "include/types.h:17"}, {"name": "vu16", "type": "volatile unsigned short", "loc": "include/types.h:18"}, {"name": "vu32", "type": "volatile unsigned int", "loc": "include/types.h:20"}, {"name": "vu64", "type": "volatile unsigned long long", "loc": "include/types.h:22"}, {"name": "vu8", "type": "volatile unsigned char", "loc": "include/types.h:16"}]